CHANGELOG.md
LICENSE.txt
MANIFEST.in
README.md
peekaboo.conf.sample
requirements.txt
ruleset.conf.sample
setup.py
PeekabooAV.egg-info/PKG-INFO
PeekabooAV.egg-info/SOURCES.txt
PeekabooAV.egg-info/dependency_links.txt
PeekabooAV.egg-info/entry_points.txt
PeekabooAV.egg-info/requires.txt
PeekabooAV.egg-info/top_level.txt
amavis/10-ask_peekaboo
peekaboo/__init__.py
peekaboo/cli.py
peekaboo/config.py
peekaboo/daemon.py
peekaboo/db.py
peekaboo/exceptions.py
peekaboo/queuing.py
peekaboo/sample.py
peekaboo/server.py
peekaboo/locale/peekaboo.pot
peekaboo/locale/de/LC_MESSAGES/peekaboo.mo
peekaboo/locale/de/LC_MESSAGES/peekaboo.po
peekaboo/ruleset/__init__.py
peekaboo/ruleset/engine.py
peekaboo/ruleset/expressions.py
peekaboo/ruleset/rules.py
peekaboo/toolbox/__init__.py
peekaboo/toolbox/cuckoo.py
peekaboo/toolbox/file.py
peekaboo/toolbox/ole.py
peekaboo/toolbox/peekabooyar.py
systemd/peekaboo.service