Metadata-Version: 2.1
Name: PeekabooAV
Version: 2.0.2
Summary: Peekaboo Extended Email Attachment Behavior Observation Owl
Home-page: https://github.com/scVENUS/PeekabooAV.git
Author: Felix Bauer
Author-email: felix.bauer@atos.net
License: GPLv3
Download-URL: https://github.com/scVENUS/PeekabooAV/archive/master.zip
Keywords: Cuckoo,Amavis
Platform: UNKNOWN
Classifier: Development Status :: 4 - Beta
Classifier: Operating System :: POSIX
Classifier: Programming Language :: Python
Classifier: Programming Language :: Python :: 2
Classifier: Programming Language :: Python :: 3
Classifier: License :: OSI Approved :: GNU General Public License v3 (GPLv3)
Classifier: Natural Language :: English
Classifier: Natural Language :: German
Classifier: Topic :: Communications :: Email :: Filters
License-File: LICENSE.txt
